fds/__init__.py
fds/sdk/__init__.py
fds/sdk/RealTimePriceAlerting/__init__.py
fds/sdk/RealTimePriceAlerting/api_client.py
fds/sdk/RealTimePriceAlerting/configuration.py
fds/sdk/RealTimePriceAlerting/exceptions.py
fds/sdk/RealTimePriceAlerting/model_utils.py
fds/sdk/RealTimePriceAlerting/rest.py
fds/sdk/RealTimePriceAlerting/api/__init__.py
fds/sdk/RealTimePriceAlerting/api/alerting_api.py
fds/sdk/RealTimePriceAlerting/apis/__init__.py
fds/sdk/RealTimePriceAlerting/model/__init__.py
fds/sdk/RealTimePriceAlerting/model/attributes_member.py
fds/sdk/RealTimePriceAlerting/model/cursor_based_pagination_output_object.py
fds/sdk/RealTimePriceAlerting/model/get_alerting_prices_basic_alert_get_data_notification_status_items.py
fds/sdk/RealTimePriceAlerting/model/get_alerting_prices_basic_alert_get_data_notification_status_items_channel.py
fds/sdk/RealTimePriceAlerting/model/get_alerting_prices_basic_alert_list_data_items.py
fds/sdk/RealTimePriceAlerting/model/get_alerting_prices_basic_alert_list_data_items_notification.py
fds/sdk/RealTimePriceAlerting/model/get_alerting_prices_basic_alert_list_data_items_trigger.py
fds/sdk/RealTimePriceAlerting/model/get_alerting_prices_basic_alert_list_data_items_trigger_notification.py
fds/sdk/RealTimePriceAlerting/model/get_alerting_prices_basic_alert_list_data_items_trigger_notification_channel.py
fds/sdk/RealTimePriceAlerting/model/get_alerting_prices_basic_alert_list_data_items_trigger_price.py
fds/sdk/RealTimePriceAlerting/model/get_alerting_prices_basic_alert_list_data_items_trigger_range.py
fds/sdk/RealTimePriceAlerting/model/get_alerting_prices_basic_alert_list_data_notification_status_items.py
fds/sdk/RealTimePriceAlerting/model/get_alerting_prices_basic_alert_list_data_notification_status_items_channel.py
fds/sdk/RealTimePriceAlerting/model/get_alerting_prices_basic_trigger_get_data_notification_channel_items.py
fds/sdk/RealTimePriceAlerting/model/inline_response200.py
fds/sdk/RealTimePriceAlerting/model/inline_response2001.py
fds.sdk.RealTimePriceAlerting-0.12.1.dist-info/LICENSE
fds.sdk.RealTimePriceAlerting-0.12.1.dist-info/METADATA
fds.sdk.RealTimePriceAlerting-0.12.1.dist-info/WHEEL
fds.sdk.RealTimePriceAlerting-0.12.1.dist-info/top_level.txt
fds.sdk.RealTimePriceAlerting-0.12.1.dist-info/RECORD
